{
  "api_url": "https://us-central1-habitat-19883.cloudfunctions.net/api/search",
  "api_key": "PUT_YOUR_API_KEY_HERE",
  "environment_id": "30eacaa5-cebb-466a-870e-e02fde1cc371",
  "only_standby": true,
  "search_in": "campaign",
  "include_descendants": true,
  "limit": 20,
  "poll_interval_sec": 1800,
  "request_timeout_sec": 15,
  "default_duration_ms": 10000,
  "cache_dir": "./media_cache",
  "state_dir": "",
  "offline_fallback": true,
  "offline_max_age_hours": 0,
  "require_full_download_before_switch": true,
  "disable_cleanup_when_offline": true,
  "cache_max_files": 0,
  "cache_max_bytes": 0,
  "mpv_path": "mpv",
  "ipc_path": "",
  "rotation_deg": 0,
  "hotkeys_enabled": true,
  "hotkey_open_key": "Ctrl+s",
  "config_ui_enabled": true,
  "config_ui_bind": "127.0.0.1",
  "config_ui_port": 8765,
  "low_resource_mode": false,
  "telemetry_enabled": true,
  "telemetry_url": "https://api.dadooh.ai/api/v1/interact/telemetry",
  "telemetry_interval_sec": 60,
  "telemetry_timeout_sec": 10,
  "station_id": "",
  "preload_next": true,
  "mute": false,
  "lock_input": true,
  "hwdec": "auto",
  "log_file": "",
  "log_max_bytes": 5000000,
  "log_backup_count": 3,
  "watchdog_interval_sec": 10,
  "status_file": "",
  "status_interval_sec": 5,
  "cleanup_interval_sec": 1800
}
